{
"meta":{"test_sets":[],"test_metrics":[],"learn_metrics":[{"best_value":"Min","name":"Logloss"}],"launch_mode":"Train","parameters":"","iteration_count":600,"learn_sets":["learn"],"name":"experiment"},
"iterations":[
{"learn":[0.5387182963],"iteration":0,"passed_time":0.07196800347,"remaining_time":43.10883408},
{"learn":[0.4255669381],"iteration":1,"passed_time":0.1487876709,"remaining_time":44.48751359},
{"learn":[0.3535143467],"iteration":2,"passed_time":0.22090095,"remaining_time":43.95928906},
{"learn":[0.306011001],"iteration":3,"passed_time":0.2941606691,"remaining_time":43.82993969},
{"learn":[0.2759299397],"iteration":4,"passed_time":0.368272967,"remaining_time":43.82448307},
{"learn":[0.2538029519],"iteration":5,"passed_time":0.4414781287,"remaining_time":43.70633475},
{"learn":[0.2392769008],"iteration":6,"passed_time":0.5110303236,"remaining_time":43.29156884},
{"learn":[0.2278358819],"iteration":7,"passed_time":0.5820821458,"remaining_time":43.07407879},
{"learn":[0.2191687603],"iteration":8,"passed_time":0.65252727,"remaining_time":42.84929073},
{"learn":[0.2128363354],"iteration":9,"passed_time":0.7219597539,"remaining_time":42.59562548},
{"learn":[0.2070483053],"iteration":10,"passed_time":0.7961941867,"remaining_time":42.63257963},
{"learn":[0.2030237165],"iteration":11,"passed_time":0.865043659,"remaining_time":42.38713929},
{"learn":[0.1987165141],"iteration":12,"passed_time":0.9422980216,"remaining_time":42.5483799},
{"learn":[0.1960953557],"iteration":13,"passed_time":1.016151458,"remaining_time":42.53319676},
{"learn":[0.1930469906],"iteration":14,"passed_time":1.094180418,"remaining_time":42.67303628},
{"learn":[0.1907135866],"iteration":15,"passed_time":1.169163407,"remaining_time":42.67446434},
{"learn":[0.1888913931],"iteration":16,"passed_time":1.239073446,"remaining_time":42.49293052},
{"learn":[0.1875030227],"iteration":17,"passed_time":1.312022967,"remaining_time":42.42207593},
{"learn":[0.1859498464],"iteration":18,"passed_time":1.380006228,"remaining_time":42.19913782},
{"learn":[0.1849136388],"iteration":19,"passed_time":1.451951011,"remaining_time":42.10657932},
{"learn":[0.1836420564],"iteration":20,"passed_time":1.524453364,"remaining_time":42.03135703},
{"learn":[0.1820901801],"iteration":21,"passed_time":1.602496777,"remaining_time":42.10196078},
{"learn":[0.1810721057],"iteration":22,"passed_time":1.676115861,"remaining_time":42.04864573},
{"learn":[0.1803756572],"iteration":23,"passed_time":1.752651973,"remaining_time":42.06364736},
{"learn":[0.179342281],"iteration":24,"passed_time":1.823731414,"remaining_time":41.94582252},
{"learn":[0.17862965],"iteration":25,"passed_time":1.894112873,"remaining_time":41.81618419},
{"learn":[0.1779281712],"iteration":26,"passed_time":1.961789296,"remaining_time":41.63352839},
{"learn":[0.1768115054],"iteration":27,"passed_time":2.039723759,"remaining_time":41.66864251},
{"learn":[0.1758687352],"iteration":28,"passed_time":2.122718584,"remaining_time":41.79559694},
{"learn":[0.17525509],"iteration":29,"passed_time":2.211358627,"remaining_time":42.01581392},
{"learn":[0.174796918],"iteration":30,"passed_time":2.30324615,"remaining_time":42.2757116},
{"learn":[0.174298285],"iteration":31,"passed_time":2.398570552,"remaining_time":42.57462729},
{"learn":[0.1737089415],"iteration":32,"passed_time":2.495771504,"remaining_time":42.88189221},
{"learn":[0.1731211362],"iteration":33,"passed_time":2.592140298,"remaining_time":43.15151202},
{"learn":[0.1724728562],"iteration":34,"passed_time":2.692058889,"remaining_time":43.45752207},
{"learn":[0.171555203],"iteration":35,"passed_time":2.800468435,"remaining_time":43.87400548},
{"learn":[0.1712777091],"iteration":36,"passed_time":2.890518755,"remaining_time":43.98275835},
{"learn":[0.1705104239],"iteration":37,"passed_time":2.992576344,"remaining_time":44.25862909},
{"learn":[0.170012954],"iteration":38,"passed_time":3.072762371,"remaining_time":44.20050488},
{"learn":[0.1695333407],"iteration":39,"passed_time":3.165051589,"remaining_time":44.31072225},
{"learn":[0.1691930448],"iteration":40,"passed_time":3.252135768,"remaining_time":44.34009499},
{"learn":[0.1687274723],"iteration":41,"passed_time":3.34113694,"remaining_time":44.38939078},
{"learn":[0.1682074201],"iteration":42,"passed_time":3.430750005,"remaining_time":44.4401803},
{"learn":[0.1678824652],"iteration":43,"passed_time":3.513576918,"remaining_time":44.3988356},
{"learn":[0.1673903916],"iteration":44,"passed_time":3.598824018,"remaining_time":44.38549623},
{"learn":[0.167027102],"iteration":45,"passed_time":3.687607852,"remaining_time":44.41162499},
{"learn":[0.1667082292],"iteration":46,"passed_time":3.775416332,"remaining_time":44.42138791},
{"learn":[0.1664120925],"iteration":47,"passed_time":3.8608211,"remaining_time":44.39944265},
{"learn":[0.1659159766],"iteration":48,"passed_time":3.939204636,"remaining_time":44.29595417},
{"learn":[0.1655338367],"iteration":49,"passed_time":4.030315262,"remaining_time":44.33346788},
{"learn":[0.165165533],"iteration":50,"passed_time":4.113741036,"remaining_time":44.28321233},
{"learn":[0.164962242],"iteration":51,"passed_time":4.197689813,"remaining_time":44.23719265},
{"learn":[0.1646341957],"iteration":52,"passed_time":4.286248034,"remaining_time":44.23731462},
{"learn":[0.1643916492],"iteration":53,"passed_time":4.372587573,"remaining_time":44.21171879},
{"learn":[0.1641705133],"iteration":54,"passed_time":4.457493224,"remaining_time":44.16970558},
{"learn":[0.1638438782],"iteration":55,"passed_time":4.543740071,"remaining_time":44.13918927},
{"learn":[0.1636370709],"iteration":56,"passed_time":4.625602728,"remaining_time":44.0649523},
{"learn":[0.1632121041],"iteration":57,"passed_time":4.715880378,"remaining_time":44.06908905},
{"learn":[0.1629700429],"iteration":58,"passed_time":4.799983301,"remaining_time":44.0134062},
{"learn":[0.1628036703],"iteration":59,"passed_time":4.889007642,"remaining_time":44.00106878},
{"learn":[0.1625306974],"iteration":60,"passed_time":4.978970078,"remaining_time":43.9945061},
{"learn":[0.1621475726],"iteration":61,"passed_time":5.067075419,"remaining_time":43.96913831},
{"learn":[0.1618605149],"iteration":62,"passed_time":5.152534695,"remaining_time":43.9192243},
{"learn":[0.1617516336],"iteration":63,"passed_time":5.235379799,"remaining_time":43.84630581},
{"learn":[0.1615204718],"iteration":64,"passed_time":5.31825163,"remaining_time":43.77330188},
{"learn":[0.1613595801],"iteration":65,"passed_time":5.40387834,"remaining_time":43.72228838},
{"learn":[0.1611561695],"iteration":66,"passed_time":5.489250682,"remaining_time":43.66821811},
{"learn":[0.1609845247],"iteration":67,"passed_time":5.565510525,"remaining_time":43.54193529},
{"learn":[0.1607575546],"iteration":68,"passed_time":5.650525352,"remaining_time":43.48447771},
{"learn":[0.1606781273],"iteration":69,"passed_time":5.738432387,"remaining_time":43.44813093},
{"learn":[0.1604842519],"iteration":70,"passed_time":5.821632107,"remaining_time":43.37525894},
{"learn":[0.1603513224],"iteration":71,"passed_time":5.907835,"remaining_time":43.32412333},
{"learn":[0.1602125089],"iteration":72,"passed_time":5.990352511,"remaining_time":43.24542155},
{"learn":[0.1600877382],"iteration":73,"passed_time":6.078016983,"remaining_time":43.2032018},
{"learn":[0.1599660233],"iteration":74,"passed_time":6.167208214,"remaining_time":43.1704575},
{"learn":[0.1598433891],"iteration":75,"passed_time":6.250074748,"remaining_time":43.09262063},
{"learn":[0.1597272598],"iteration":76,"passed_time":6.331648551,"remaining_time":43.00587263},
{"learn":[0.1594654122],"iteration":77,"passed_time":6.42176111,"remaining_time":42.97640127},
{"learn":[0.1592440617],"iteration":78,"passed_time":6.503876621,"remaining_time":42.89265468},
{"learn":[0.1591379029],"iteration":79,"passed_time":6.586901752,"remaining_time":42.81486139},
{"learn":[0.1590497888],"iteration":80,"passed_time":6.671952467,"remaining_time":42.74991766},
{"learn":[0.1589600413],"iteration":81,"passed_time":6.760483352,"remaining_time":42.706468},
{"learn":[0.1588760759],"iteration":82,"passed_time":6.844658922,"remaining_time":42.63480317},
{"learn":[0.1587555978],"iteration":83,"passed_time":6.927535614,"remaining_time":42.55486163},
{"learn":[0.1585940671],"iteration":84,"passed_time":7.024046364,"remaining_time":42.55745738},
{"learn":[0.1583682079],"iteration":85,"passed_time":7.148172879,"remaining_time":42.72280069},
{"learn":[0.1582819185],"iteration":86,"passed_time":7.24658329,"remaining_time":42.72985319},
{"learn":[0.158132399],"iteration":87,"passed_time":7.345668887,"remaining_time":42.73843716},
{"learn":[0.158033065],"iteration":88,"passed_time":7.449430484,"remaining_time":42.77144918},
{"learn":[0.1579278872],"iteration":89,"passed_time":7.559966594,"remaining_time":42.8398107},
{"learn":[0.1577952676],"iteration":90,"passed_time":7.666039879,"remaining_time":42.879278},
{"learn":[0.1576591032],"iteration":91,"passed_time":7.771129452,"remaining_time":42.91014958},
{"learn":[0.1574646995],"iteration":92,"passed_time":7.874739332,"remaining_time":42.93003055},
{"learn":[0.1573719568],"iteration":93,"passed_time":7.972728083,"remaining_time":42.91702564},
{"learn":[0.1572634846],"iteration":94,"passed_time":8.180532752,"remaining_time":43.48598989},
{"learn":[0.1571871747],"iteration":95,"passed_time":8.357285471,"remaining_time":43.87574872},
{"learn":[0.1570159814],"iteration":96,"passed_time":8.501969647,"remaining_time":44.08753332},
{"learn":[0.1569014679],"iteration":97,"passed_time":8.638537592,"remaining_time":44.25046807},
{"learn":[0.156819944],"iteration":98,"passed_time":8.7634389,"remaining_time":44.34831201},
{"learn":[0.156759491],"iteration":99,"passed_time":8.882461654,"remaining_time":44.41230827},
{"learn":[0.1566769023],"iteration":100,"passed_time":8.98628293,"remaining_time":44.39757606},
{"learn":[0.156553539],"iteration":101,"passed_time":9.118747687,"remaining_time":44.52094459},
{"learn":[0.1565021717],"iteration":102,"passed_time":9.250136119,"remaining_time":44.63415195},
{"learn":[0.1564064226],"iteration":103,"passed_time":9.379969857,"remaining_time":44.73524086},
{"learn":[0.1563186429],"iteration":104,"passed_time":9.500004016,"remaining_time":44.78573322},
{"learn":[0.1562490685],"iteration":105,"passed_time":9.62662179,"remaining_time":44.86369023},
{"learn":[0.1561954307],"iteration":106,"passed_time":9.76547724,"remaining_time":44.99420822},
{"learn":[0.1561186809],"iteration":107,"passed_time":9.886323539,"remaining_time":45.03769612},
{"learn":[0.1560513371],"iteration":108,"passed_time":10.00177663,"remaining_time":45.05387453},
{"learn":[0.1559590533],"iteration":109,"passed_time":10.1997578,"remaining_time":45.43528474},
{"learn":[0.1558842379],"iteration":110,"passed_time":10.37956788,"remaining_time":45.72620446},
{"learn":[0.1558163594],"iteration":111,"passed_time":10.53957319,"remaining_time":45.92242603},
{"learn":[0.1557357205],"iteration":112,"passed_time":10.66916796,"remaining_time":45.98128139},
{"learn":[0.1556353784],"iteration":113,"passed_time":10.78431017,"remaining_time":45.97521702},
{"learn":[0.1554772346],"iteration":114,"passed_time":10.89416399,"remaining_time":45.94495248},
{"learn":[0.1552747077],"iteration":115,"passed_time":11.01188692,"remaining_time":45.94614887},
{"learn":[0.1551791503],"iteration":116,"passed_time":11.11828132,"remaining_time":45.89854595},
{"learn":[0.1551171011],"iteration":117,"passed_time":11.22773558,"remaining_time":45.86244533},
{"learn":[0.1550074505],"iteration":118,"passed_time":11.34288753,"remaining_time":45.84814202},
{"learn":[0.1549646994],"iteration":119,"passed_time":11.45654261,"remaining_time":45.82617046},
{"learn":[0.1548729688],"iteration":120,"passed_time":11.60676718,"remaining_time":45.94745023},
{"learn":[0.1547811183],"iteration":121,"passed_time":11.84755149,"remaining_time":46.41909518},
{"learn":[0.1546808005],"iteration":122,"passed_time":12.07030504,"remaining_time":46.80923175},
{"learn":[0.1546022922],"iteration":123,"passed_time":12.3198101,"remaining_time":47.29217427},
{"learn":[0.1545309448],"iteration":124,"passed_time":12.50557542,"remaining_time":47.52118658},
{"learn":[0.1544341275],"iteration":125,"passed_time":12.6689367,"remaining_time":47.65933331},
{"learn":[0.1543644409],"iteration":126,"passed_time":12.8334767,"remaining_time":47.79712188},
{"learn":[0.1542163062],"iteration":127,"passed_time":13.10664408,"remaining_time":48.33075005},
{"learn":[0.1541150076],"iteration":128,"passed_time":13.33092022,"remaining_time":48.67335986},
{"learn":[0.154032257],"iteration":129,"passed_time":13.52912821,"remaining_time":48.91300197},
{"learn":[0.1539348533],"iteration":130,"passed_time":13.72506596,"remaining_time":49.13783157},
{"learn":[0.1538725924],"iteration":131,"passed_time":13.85305826,"remaining_time":49.11538837},
{"learn":[0.1538119046],"iteration":132,"passed_time":13.96492301,"remaining_time":49.03472966},
{"learn":[0.1537130905],"iteration":133,"passed_time":14.07436247,"remaining_time":48.94517099},
{"learn":[0.1536575791],"iteration":134,"passed_time":14.18920209,"remaining_time":48.8739183},
{"learn":[0.1535511815],"iteration":135,"passed_time":14.29977256,"remaining_time":48.78745933},
{"learn":[0.1534874016],"iteration":136,"passed_time":14.41241823,"remaining_time":48.70766159},
{"learn":[0.1534064183],"iteration":137,"passed_time":14.52531181,"remaining_time":48.6282178},
{"learn":[0.1533591112],"iteration":138,"passed_time":14.63411533,"remaining_time":48.53472781},
{"learn":[0.153296551],"iteration":139,"passed_time":14.75479797,"remaining_time":48.48005047},
{"learn":[0.1532268896],"iteration":140,"passed_time":14.91823625,"remaining_time":48.56362013},
{"learn":[0.1531428588],"iteration":141,"passed_time":15.08638126,"remaining_time":48.65889166},
{"learn":[0.1530809189],"iteration":142,"passed_time":15.24385675,"remaining_time":48.71638135},
{"learn":[0.1529778586],"iteration":143,"passed_time":15.41855571,"remaining_time":48.82542642},
{"learn":[0.1529450977],"iteration":144,"passed_time":15.61568326,"remaining_time":49.00093713},
{"learn":[0.1528766127],"iteration":145,"passed_time":15.80616186,"remaining_time":49.15066771},
{"learn":[0.1527797755],"iteration":146,"passed_time":15.9931453,"remaining_time":49.28499877},
{"learn":[0.1527179571],"iteration":147,"passed_time":16.20044979,"remaining_time":49.47704937},
{"learn":[0.1526226814],"iteration":148,"passed_time":16.36805078,"remaining_time":49.5435631},
{"learn":[0.1525674356],"iteration":149,"passed_time":16.54393243,"remaining_time":49.63179729},
{"learn":[0.1525227856],"iteration":150,"passed_time":16.70764928,"remaining_time":49.6803611},
{"learn":[0.1524674989],"iteration":151,"passed_time":16.86274602,"remaining_time":49.70072513},
{"learn":[0.1523798512],"iteration":152,"passed_time":17.03629758,"remaining_time":49.77271254},
{"learn":[0.152314809],"iteration":153,"passed_time":17.17797803,"remaining_time":49.74920909},
{"learn":[0.1522468951],"iteration":154,"passed_time":17.29780609,"remaining_time":49.66144329},
{"learn":[0.1521279006],"iteration":155,"passed_time":17.39929281,"remaining_time":49.52106414},
{"learn":[0.152080726],"iteration":156,"passed_time":17.49708447,"remaining_time":49.37075428},
{"learn":[0.1519981214],"iteration":157,"passed_time":17.60293614,"remaining_time":49.2436568},
{"learn":[0.1519357967],"iteration":158,"passed_time":17.69982325,"remaining_time":49.0919626},
{"learn":[0.1518710952],"iteration":159,"passed_time":17.79139878,"remaining_time":48.92634665},
{"learn":[0.1518151147],"iteration":160,"passed_time":17.88612618,"remaining_time":48.77024467},
{"learn":[0.1517143606],"iteration":161,"passed_time":18.0169512,"remaining_time":48.71249768},
{"learn":[0.151674203],"iteration":162,"passed_time":18.28938778,"remaining_time":49.03351202},
{"learn":[0.1516227078],"iteration":163,"passed_time":18.41494295,"remaining_time":48.95679954},
{"learn":[0.1515764632],"iteration":164,"passed_time":18.5399315,"remaining_time":48.87800123},
{"learn":[0.1515290969],"iteration":165,"passed_time":18.64654111,"remaining_time":48.75059542},
{"learn":[0.1514579047],"iteration":166,"passed_time":18.76338136,"remaining_time":48.64996483},
{"learn":[0.1513815414],"iteration":167,"passed_time":18.87212241,"remaining_time":48.52831477},
{"learn":[0.1512830626],"iteration":168,"passed_time":18.97584242,"remaining_time":48.39401234},
{"learn":[0.1512183596],"iteration":169,"passed_time":19.07470589,"remaining_time":48.24778548},
{"learn":[0.151152386],"iteration":170,"passed_time":19.17637239,"remaining_time":48.10914478},
{"learn":[0.1510940192],"iteration":171,"passed_time":19.27412671,"remaining_time":47.96119902},
{"learn":[0.1510658051],"iteration":172,"passed_time":19.36470999,"remaining_time":47.79613392},
{"learn":[0.1510261401],"iteration":173,"passed_time":19.46455353,"remaining_time":47.65459658},
{"learn":[0.1509611623],"iteration":174,"passed_time":19.56301907,"remaining_time":47.51018916},
{"learn":[0.1509172345],"iteration":175,"passed_time":19.66351544,"remaining_time":47.3711963},
{"learn":[0.1508760413],"iteration":176,"passed_time":19.75676144,"remaining_time":47.21531125},
{"learn":[0.1508330497],"iteration":177,"passed_time":19.85450425,"remaining_time":47.07079098},
{"learn":[0.1507857816],"iteration":178,"passed_time":19.95647285,"remaining_time":46.93673222},
{"learn":[0.1507369459],"iteration":179,"passed_time":20.0534516,"remaining_time":46.79138706},
{"learn":[0.1507033249],"iteration":180,"passed_time":20.14722143,"remaining_time":46.63914794},
{"learn":[0.1506635803],"iteration":181,"passed_time":20.24774428,"remaining_time":46.50306104},
{"learn":[0.1506300234],"iteration":182,"passed_time":20.34871707,"remaining_time":46.36838808},
{"learn":[0.1505670236],"iteration":183,"passed_time":20.45601331,"remaining_time":46.24837792},
{"learn":[0.1505223915],"iteration":184,"passed_time":20.57195655,"remaining_time":46.14790254},
{"learn":[0.1504469488],"iteration":185,"passed_time":20.68026406,"remaining_time":46.03026517},
{"learn":[0.1503813221],"iteration":186,"passed_time":20.79123819,"remaining_time":45.91861697},
{"learn":[0.1503446925],"iteration":187,"passed_time":20.89401982,"remaining_time":45.78902215},
{"learn":[0.1503038775],"iteration":188,"passed_time":20.99749328,"remaining_time":45.66121554},
{"learn":[0.1502621752],"iteration":189,"passed_time":21.09948252,"remaining_time":45.53046229},
{"learn":[0.1502207882],"iteration":190,"passed_time":21.20672906,"remaining_time":45.41126799},
{"learn":[0.1501936],"iteration":191,"passed_time":21.30742819,"remaining_time":45.27828491},
{"learn":[0.1501683641],"iteration":192,"passed_time":21.4023678,"remaining_time":45.13349064},
{"learn":[0.1501201136],"iteration":193,"passed_time":21.50129877,"remaining_time":44.9975634},
{"learn":[0.1500945773],"iteration":194,"passed_time":21.60067553,"remaining_time":44.86294149},
{"learn":[0.1500395496],"iteration":195,"passed_time":21.70901399,"remaining_time":44.74715129},
{"learn":[0.1499907516],"iteration":196,"passed_time":21.89129478,"remaining_time":44.78269947},
{"learn":[0.149950232],"iteration":197,"passed_time":21.98967738,"remaining_time":44.64570862},
{"learn":[0.1499144944],"iteration":198,"passed_time":22.12358133,"remaining_time":44.58068399},
{"learn":[0.1498721301],"iteration":199,"passed_time":22.22971009,"remaining_time":44.45942018},
{"learn":[0.1498159493],"iteration":200,"passed_time":22.42640431,"remaining_time":44.51808616},
{"learn":[0.1497371865],"iteration":201,"passed_time":22.55062243,"remaining_time":44.43142439},
{"learn":[0.1497041277],"iteration":202,"passed_time":22.64892406,"remaining_time":44.29370862},
{"learn":[0.1496260207],"iteration":203,"passed_time":22.75068778,"remaining_time":44.16309982},
{"learn":[0.1495856995],"iteration":204,"passed_time":22.84298978,"remaining_time":44.01454128},
{"learn":[0.1495397616],"iteration":205,"passed_time":22.93819298,"remaining_time":43.87207784},
{"learn":[0.1495007625],"iteration":206,"passed_time":23.03585834,"remaining_time":43.73474555},
{"learn":[0.1494686338],"iteration":207,"passed_time":23.13550328,"remaining_time":43.60152542},
{"learn":[0.1494081599],"iteration":208,"passed_time":23.24727248,"remaining_time":43.4913088},
{"learn":[0.1493633933],"iteration":209,"passed_time":23.35798874,"remaining_time":43.37912194},
{"learn":[0.1492939609],"iteration":210,"passed_time":23.47172419,"remaining_time":43.27251522},
{"learn":[0.1492548536],"iteration":211,"passed_time":23.57597394,"remaining_time":43.1484806},
{"learn":[0.1492071121],"iteration":212,"passed_time":23.69684667,"remaining_time":43.05483409},
{"learn":[0.1491756603],"iteration":213,"passed_time":23.8125866,"remaining_time":42.9516749},
{"learn":[0.1491275341],"iteration":214,"passed_time":23.92077239,"remaining_time":42.83487148},
{"learn":[0.149096151],"iteration":215,"passed_time":24.01513818,"remaining_time":42.69357899},
{"learn":[0.1490632413],"iteration":216,"passed_time":24.11399937,"remaining_time":42.56065327},
{"learn":[0.1490204445],"iteration":217,"passed_time":24.21114992,"remaining_time":42.42504251},
{"learn":[0.1489674594],"iteration":218,"passed_time":24.33794339,"remaining_time":42.34135357},
{"learn":[0.1489022002],"iteration":219,"passed_time":24.43840852,"remaining_time":42.21179654},
{"learn":[0.1488723843],"iteration":220,"passed_time":24.52967834,"remaining_time":42.06673345},
{"learn":[0.1488294095],"iteration":221,"passed_time":24.63878887,"remaining_time":41.95253241},
{"learn":[0.1487887811],"iteration":222,"passed_time":24.73892374,"remaining_time":41.82320292},
{"learn":[0.1487623457],"iteration":223,"passed_time":24.8381929,"remaining_time":41.69268093},
{"learn":[0.1487353683],"iteration":224,"passed_time":24.93434029,"remaining_time":41.55723381},
{"learn":[0.1487031628],"iteration":225,"passed_time":25.0978978,"remaining_time":41.53368929},
{"learn":[0.1486577056],"iteration":226,"passed_time":25.2137063,"remaining_time":41.43045132},
{"learn":[0.1486339768],"iteration":227,"passed_time":25.31458096,"remaining_time":41.30273735},
{"learn":[0.1486085222],"iteration":228,"passed_time":25.41037218,"remaining_time":41.16702217},
{"learn":[0.148559031],"iteration":229,"passed_time":25.50647009,"remaining_time":41.03214753},
{"learn":[0.1485124698],"iteration":230,"passed_time":25.6053557,"remaining_time":40.90206169},
{"learn":[0.1484728259],"iteration":231,"passed_time":25.70611543,"remaining_time":40.77521758},
{"learn":[0.1484280914],"iteration":232,"passed_time":25.80112522,"remaining_time":40.63954059},
{"learn":[0.1483807595],"iteration":233,"passed_time":25.90689009,"remaining_time":40.52103322},
{"learn":[0.148354786],"iteration":234,"passed_time":25.99401575,"remaining_time":40.37368404},
{"learn":[0.1483209409],"iteration":235,"passed_time":26.08908878,"remaining_time":40.23910304},
{"learn":[0.1482870025],"iteration":236,"passed_time":26.18639544,"remaining_time":40.10827655},
{"learn":[0.1482517455],"iteration":237,"passed_time":26.28693879,"remaining_time":39.9826548},
{"learn":[0.1482200799],"iteration":238,"passed_time":26.38329624,"remaining_time":39.85092027},
{"learn":[0.148181258],"iteration":239,"passed_time":26.47814492,"remaining_time":39.71721737},
{"learn":[0.1481376941],"iteration":240,"passed_time":26.5765589,"remaining_time":39.58914791},
{"learn":[0.1481094445],"iteration":241,"passed_time":26.67459864,"remaining_time":39.46076988},
{"learn":[0.1480811759],"iteration":242,"passed_time":26.76941604,"remaining_time":39.32790751},
{"learn":[0.1480348143],"iteration":243,"passed_time":26.87205829,"remaining_time":39.20677356},
{"learn":[0.1480056208],"iteration":244,"passed_time":26.96865219,"remaining_time":39.07702664},
{"learn":[0.1479705906],"iteration":245,"passed_time":27.06671502,"remaining_time":38.94966307},
{"learn":[0.1479367347],"iteration":246,"passed_time":27.1661516,"remaining_time":38.82450006},
{"learn":[0.147896169],"iteration":247,"passed_time":27.26068227,"remaining_time":38.69258128},
{"learn":[0.1478728256],"iteration":248,"passed_time":27.35546454,"remaining_time":38.56131749},
{"learn":[0.1477986467],"iteration":249,"passed_time":27.45156039,"remaining_time":38.43218455},
{"learn":[0.1477740291],"iteration":250,"passed_time":27.54580608,"remaining_time":38.30074232},
{"learn":[0.1477147376],"iteration":251,"passed_time":27.64109469,"remaining_time":38.17103552},
{"learn":[0.1476814448],"iteration":252,"passed_time":27.73401905,"remaining_time":38.03835814},
{"learn":[0.1476477834],"iteration":253,"passed_time":27.83120134,"remaining_time":37.91179394},
{"learn":[0.1476036481],"iteration":254,"passed_time":27.93870649,"remaining_time":37.79942642},
{"learn":[0.1475737304],"iteration":255,"passed_time":28.04358335,"remaining_time":37.68356513},
{"learn":[0.1475565929],"iteration":256,"passed_time":28.14298547,"remaining_time":37.56048255},
{"learn":[0.1475281797],"iteration":257,"passed_time":28.24911553,"remaining_time":37.44650198},
{"learn":[0.1474931741],"iteration":258,"passed_time":28.36062668,"remaining_time":37.33966678},
{"learn":[0.1474621262],"iteration":259,"passed_time":28.46784747,"remaining_time":37.22718516},
{"learn":[0.1474209432],"iteration":260,"passed_time":28.58262607,"remaining_time":37.12456029},
{"learn":[0.1473735986],"iteration":261,"passed_time":28.69330108,"remaining_time":37.01654872},
{"learn":[0.1473156984],"iteration":262,"passed_time":28.80482126,"remaining_time":36.90959987},
{"learn":[0.1472774934],"iteration":263,"passed_time":28.90537962,"remaining_time":36.78866497},
{"learn":[0.147240053],"iteration":264,"passed_time":29.0031475,"remaining_time":36.66435627},
{"learn":[0.1471955694],"iteration":265,"passed_time":29.10384719,"remaining_time":36.54392843},
{"learn":[0.1471646426],"iteration":266,"passed_time":29.19905157,"remaining_time":36.41679465},
{"learn":[0.1471357111],"iteration":267,"passed_time":29.29995703,"remaining_time":36.2969617},
{"learn":[0.1470956182],"iteration":268,"passed_time":29.4005814,"remaining_time":36.17692358},
{"learn":[0.1470604788],"iteration":269,"passed_time":29.50373782,"remaining_time":36.06012401},
{"learn":[0.1470307644],"iteration":270,"passed_time":29.60358072,"remaining_time":35.93940242},
{"learn":[0.1469946443],"iteration":271,"passed_time":29.70622695,"remaining_time":35.82221486},
{"learn":[0.146956097],"iteration":272,"passed_time":29.80076149,"remaining_time":35.69541761},
{"learn":[0.146924042],"iteration":273,"passed_time":29.89636148,"remaining_time":35.57012351},
{"learn":[0.14689533],"iteration":274,"passed_time":29.99197614,"remaining_time":35.44506271},
{"learn":[0.1468637234],"iteration":275,"passed_time":30.09257612,"remaining_time":35.32606761},
{"learn":[0.1468064215],"iteration":276,"passed_time":30.19800124,"remaining_time":35.21283177},
{"learn":[0.1467563401],"iteration":277,"passed_time":30.30484642,"remaining_time":35.10129693},
{"learn":[0.1467340285],"iteration":278,"passed_time":30.40844401,"remaining_time":34.98605924},
{"learn":[0.1466875158],"iteration":279,"passed_time":30.52898668,"remaining_time":34.89027049},
{"learn":[0.1466613209],"iteration":280,"passed_time":30.6311856,"remaining_time":34.77348116},
{"learn":[0.1466369683],"iteration":281,"passed_time":30.73575149,"remaining_time":34.65946445},
{"learn":[0.1466095734],"iteration":282,"passed_time":30.84664784,"remaining_time":34.55260553},
{"learn":[0.1465723088],"iteration":283,"passed_time":30.95723886,"remaining_time":34.44537845},
{"learn":[0.1465467915],"iteration":284,"passed_time":31.06589906,"remaining_time":34.3359937},
{"learn":[0.1465099175],"iteration":285,"passed_time":31.18017915,"remaining_time":34.23278411},
{"learn":[0.1464775357],"iteration":286,"passed_time":31.29461956,"remaining_time":34.12967221},
{"learn":[0.1464551072],"iteration":287,"passed_time":31.39788726,"remaining_time":34.01437787},
{"learn":[0.1464301994],"iteration":288,"passed_time":31.4913487,"remaining_time":33.888614},
{"learn":[0.1463846384],"iteration":289,"passed_time":31.59261349,"remaining_time":33.77141442},
{"learn":[0.1463510453],"iteration":290,"passed_time":31.68797078,"remaining_time":33.64805144},
{"learn":[0.1463053435],"iteration":291,"passed_time":31.78376882,"remaining_time":33.52534519},
{"learn":[0.1462863501],"iteration":292,"passed_time":31.87597392,"remaining_time":33.399058},
{"learn":[0.1462216006],"iteration":293,"passed_time":31.97370559,"remaining_time":33.2787548},
{"learn":[0.1462029063],"iteration":294,"passed_time":32.06494526,"remaining_time":33.15189256},
{"learn":[0.1461779116],"iteration":295,"passed_time":32.15493196,"remaining_time":33.02398418},
{"learn":[0.1461476468],"iteration":296,"passed_time":32.24860065,"remaining_time":32.90008754},
{"learn":[0.1461228888],"iteration":297,"passed_time":32.36528078,"remaining_time":32.79971408},
{"learn":[0.1460916391],"iteration":298,"passed_time":32.46926558,"remaining_time":32.6864513},
{"learn":[0.1460690175],"iteration":299,"passed_time":32.56564893,"remaining_time":32.56564893},
{"learn":[0.1460362107],"iteration":300,"passed_time":32.66140755,"remaining_time":32.44438823},
{"learn":[0.1460047131],"iteration":301,"passed_time":32.76638966,"remaining_time":32.33239775},
{"learn":[0.1459739269],"iteration":302,"passed_time":32.87143654,"remaining_time":32.220517},
{"learn":[0.1459305227],"iteration":303,"passed_time":32.9887019,"remaining_time":32.12057816},
{"learn":[0.1458924581],"iteration":304,"passed_time":33.10142422,"remaining_time":32.01613162},
{"learn":[0.1458520235],"iteration":305,"passed_time":33.22154251,"remaining_time":31.91873692},
{"learn":[0.1458236484],"iteration":306,"passed_time":33.3401589,"remaining_time":31.81976077},
{"learn":[0.145775607],"iteration":307,"passed_time":33.45846272,"remaining_time":31.72036076},
{"learn":[0.1457390673],"iteration":308,"passed_time":33.57562239,"remaining_time":31.61976089},
{"learn":[0.1456935244],"iteration":309,"passed_time":33.69089865,"remaining_time":31.51729229},
{"learn":[0.1456553715],"iteration":310,"passed_time":33.7935604,"remaining_time":31.40301915},
{"learn":[0.1456401622],"iteration":311,"passed_time":33.88410124,"remaining_time":31.27763191},
{"learn":[0.1456184329],"iteration":312,"passed_time":33.97817089,"remaining_time":31.15570302},
{"learn":[0.1455968865],"iteration":313,"passed_time":34.07160196,"remaining_time":31.03336994},
{"learn":[0.1455699555],"iteration":314,"passed_time":34.16458203,"remaining_time":30.91081231},
{"learn":[0.145540804],"iteration":315,"passed_time":34.25622657,"remaining_time":30.7872416},
{"learn":[0.1455105949],"iteration":316,"passed_time":34.35805973,"remaining_time":30.67296815},
{"learn":[0.145484506],"iteration":317,"passed_time":34.45380971,"remaining_time":30.55337842},
{"learn":[0.1454550232],"iteration":318,"passed_time":34.54776185,"remaining_time":30.43235448},
{"learn":[0.1454213293],"iteration":319,"passed_time":34.63989098,"remaining_time":30.3099046},
{"learn":[0.1453695223],"iteration":320,"passed_time":34.73830155,"remaining_time":30.19310321},
{"learn":[0.1453442083],"iteration":321,"passed_time":34.83844988,"remaining_time":30.07791636},
{"learn":[0.1453225144],"iteration":322,"passed_time":34.92975488,"remaining_time":29.95523871},
{"learn":[0.1452875574],"iteration":323,"passed_time":35.02078873,"remaining_time":29.83252373},
{"learn":[0.1452610917],"iteration":324,"passed_time":35.11766741,"remaining_time":29.71494935},
{"learn":[0.1452338124],"iteration":325,"passed_time":35.21439512,"remaining_time":29.59737504},
{"learn":[0.1452024096],"iteration":326,"passed_time":35.31219414,"remaining_time":29.48082263},
{"learn":[0.145186199],"iteration":327,"passed_time":35.40770019,"remaining_time":29.36248308},
{"learn":[0.1451601674],"iteration":328,"passed_time":35.51020686,"remaining_time":29.25004882},
{"learn":[0.1451276784],"iteration":329,"passed_time":35.60823179,"remaining_time":29.13400783},
{"learn":[0.1451001209],"iteration":330,"passed_time":35.69964429,"remaining_time":29.01270186},
{"learn":[0.1450722921],"iteration":331,"passed_time":35.79653382,"remaining_time":28.89599718},
{"learn":[0.1450286172],"iteration":332,"passed_time":35.89333672,"remaining_time":28.77934206},
{"learn":[0.1449921058],"iteration":333,"passed_time":36.00026559,"remaining_time":28.6708702},
{"learn":[0.1449582664],"iteration":334,"passed_time":36.1145995,"remaining_time":28.56826528},
{"learn":[0.1449275186],"iteration":335,"passed_time":36.22224837,"remaining_time":28.46033801},
{"learn":[0.1448946957],"iteration":336,"passed_time":36.32865544,"remaining_time":28.35144327},
{"learn":[0.1448810035],"iteration":337,"passed_time":36.43130448,"remaining_time":28.23965022},
{"learn":[0.1448528032],"iteration":338,"passed_time":36.52563403,"remaining_time":28.12150585},
{"learn":[0.1448252117],"iteration":339,"passed_time":36.62423456,"remaining_time":28.00676761},
{"learn":[0.1447961949],"iteration":340,"passed_time":36.71880041,"remaining_time":27.88905955},
{"learn":[0.1447712848],"iteration":341,"passed_time":36.81374858,"remaining_time":27.77177524},
{"learn":[0.144751502],"iteration":342,"passed_time":36.91170118,"remaining_time":27.65687231},
{"learn":[0.144725429],"iteration":343,"passed_time":37.01577463,"remaining_time":27.54662298},
{"learn":[0.1446573131],"iteration":344,"passed_time":37.10583462,"remaining_time":27.42605168},
{"learn":[0.1446349448],"iteration":345,"passed_time":37.20884944,"remaining_time":27.31516693},
{"learn":[0.1446076832],"iteration":346,"passed_time":37.30748504,"remaining_time":27.20113463},
{"learn":[0.1445952648],"iteration":347,"passed_time":37.39414954,"remaining_time":27.07852208},
{"learn":[0.1445681602],"iteration":348,"passed_time":37.49906512,"remaining_time":26.96924168},
{"learn":[0.1445279788],"iteration":349,"passed_time":37.60514152,"remaining_time":26.86081537},
{"learn":[0.1444631772],"iteration":350,"passed_time":37.70448967,"remaining_time":26.74762942},
{"learn":[0.1444411122],"iteration":351,"passed_time":37.80523766,"remaining_time":26.63550835},
{"learn":[0.1444042566],"iteration":352,"passed_time":37.91132434,"remaining_time":26.52718728},
{"learn":[0.1443777426],"iteration":353,"passed_time":38.01200887,"remaining_time":26.41512481},
{"learn":[0.1443662049],"iteration":354,"passed_time":38.11051563,"remaining_time":26.30162346},
{"learn":[0.1443271157],"iteration":355,"passed_time":38.22466484,"remaining_time":26.19892759},
{"learn":[0.1443094338],"iteration":356,"passed_time":38.32148184,"remaining_time":26.08436999},
{"learn":[0.1442899127],"iteration":357,"passed_time":38.43138032,"remaining_time":25.97875429},
{"learn":[0.144271531],"iteration":358,"passed_time":38.53495606,"remaining_time":25.86887022},
{"learn":[0.1442385597],"iteration":359,"passed_time":38.64359649,"remaining_time":25.76239766},
{"learn":[0.1442102384],"iteration":360,"passed_time":38.75036509,"remaining_time":25.65467384},
{"learn":[0.1441827884],"iteration":361,"passed_time":38.84076793,"remaining_time":25.53619549},
{"learn":[0.1441732736],"iteration":362,"passed_time":38.9311964,"remaining_time":25.41788856},
{"learn":[0.1441484528],"iteration":363,"passed_time":39.02248806,"remaining_time":25.30029446},
{"learn":[0.1440943444],"iteration":364,"passed_time":39.12767233,"remaining_time":25.19178903},
{"learn":[0.1440735737],"iteration":365,"passed_time":39.22011984,"remaining_time":25.07515859},
{"learn":[0.1440468428],"iteration":366,"passed_time":39.32092686,"remaining_time":24.96396719},
{"learn":[0.1440269612],"iteration":367,"passed_time":39.41224862,"remaining_time":24.84685239},
{"learn":[0.1439972684],"iteration":368,"passed_time":39.51298877,"remaining_time":24.73577346},
{"learn":[0.1439609473],"iteration":369,"passed_time":39.60644631,"remaining_time":24.62022338},
{"learn":[0.1439415955],"iteration":370,"passed_time":39.70560408,"remaining_time":24.50831088},
{"learn":[0.1439078567],"iteration":371,"passed_time":39.80131618,"remaining_time":24.39435508},
{"learn":[0.1438946435],"iteration":372,"passed_time":39.88816147,"remaining_time":24.27510095},
{"learn":[0.1438718546],"iteration":373,"passed_time":39.98743473,"remaining_time":24.16353008},
{"learn":[0.1438436594],"iteration":374,"passed_time":40.08180033,"remaining_time":24.0490802},
{"learn":[0.1438245809],"iteration":375,"passed_time":40.17373087,"remaining_time":23.93328648},
{"learn":[0.1437927843],"iteration":376,"passed_time":40.27089717,"remaining_time":23.82071636},
{"learn":[0.1437671849],"iteration":377,"passed_time":40.37283104,"remaining_time":23.71102775},
{"learn":[0.1437373377],"iteration":378,"passed_time":40.47769624,"remaining_time":23.60308937},
{"learn":[0.1437199393],"iteration":379,"passed_time":40.5718734,"remaining_time":23.48897933},
{"learn":[0.143699555],"iteration":380,"passed_time":40.67331082,"remaining_time":23.37914716},
{"learn":[0.143683598],"iteration":381,"passed_time":40.76533716,"remaining_time":23.26398822},
{"learn":[0.1436582236],"iteration":382,"passed_time":40.86506321,"remaining_time":23.15331258},
{"learn":[0.1436195831],"iteration":383,"passed_time":40.96078584,"remaining_time":23.04044203},
{"learn":[0.1435903919],"iteration":384,"passed_time":41.06168721,"remaining_time":22.9305526},
{"learn":[0.1435614051],"iteration":385,"passed_time":41.15974854,"remaining_time":22.8191352},
{"learn":[0.1435403832],"iteration":386,"passed_time":41.2580249,"remaining_time":22.70790518},
{"learn":[0.1435107412],"iteration":387,"passed_time":41.35670771,"remaining_time":22.59696401},
{"learn":[0.14348058],"iteration":388,"passed_time":41.46061075,"remaining_time":22.4889174},
{"learn":[0.1434538729],"iteration":389,"passed_time":41.56567275,"remaining_time":22.38151609},
{"learn":[0.1434187994],"iteration":390,"passed_time":41.66703606,"remaining_time":22.27214971},
{"learn":[0.1433886926],"iteration":391,"passed_time":41.75898893,"remaining_time":22.15783086},
{"learn":[0.1433745675],"iteration":392,"passed_time":41.84613912,"remaining_time":22.04109618},
{"learn":[0.1433600054],"iteration":393,"passed_time":41.93738694,"remaining_time":21.92665408},
{"learn":[0.1433383034],"iteration":394,"passed_time":42.03840011,"remaining_time":21.81739752},
{"learn":[0.1433112131],"iteration":395,"passed_time":42.1326528,"remaining_time":21.70469992},
{"learn":[0.1432841268],"iteration":396,"passed_time":42.23147386,"remaining_time":21.59443122},
{"learn":[0.1432623295],"iteration":397,"passed_time":42.31958149,"remaining_time":21.47878257},
{"learn":[0.1432469283],"iteration":398,"passed_time":42.41689992,"remaining_time":21.36791199},
{"learn":[0.1432210914],"iteration":399,"passed_time":42.54361353,"remaining_time":21.27180676},
{"learn":[0.143202679],"iteration":400,"passed_time":42.65424869,"remaining_time":21.1675698},
{"learn":[0.143187654],"iteration":401,"passed_time":42.76523566,"remaining_time":21.06347428},
{"learn":[0.1431613566],"iteration":402,"passed_time":42.89994912,"remaining_time":20.97094287},
{"learn":[0.1431484807],"iteration":403,"passed_time":43.01526239,"remaining_time":20.86879067},
{"learn":[0.1431165081],"iteration":404,"passed_time":43.13257567,"remaining_time":20.76753643},
{"learn":[0.143077786],"iteration":405,"passed_time":43.24386696,"remaining_time":20.66332559},
{"learn":[0.1430513622],"iteration":406,"passed_time":43.35207204,"remaining_time":20.55761647},
{"learn":[0.1430140859],"iteration":407,"passed_time":43.46650107,"remaining_time":20.45482403},
{"learn":[0.1429882759],"iteration":408,"passed_time":43.57122729,"remaining_time":20.34744355},
{"learn":[0.1429695151],"iteration":409,"passed_time":43.66610724,"remaining_time":20.23551311},
{"learn":[0.1429485236],"iteration":410,"passed_time":43.76469069,"remaining_time":20.12536871},
{"learn":[0.1429146572],"iteration":411,"passed_time":43.86251227,"remaining_time":20.01493278},
{"learn":[0.1428888283],"iteration":412,"passed_time":43.96231652,"remaining_time":19.90545567},
{"learn":[0.1428679386],"iteration":413,"passed_time":44.06423723,"remaining_time":19.79697615},
{"learn":[0.1428461523],"iteration":414,"passed_time":44.16147423,"remaining_time":19.68644032},
{"learn":[0.142833668],"iteration":415,"passed_time":44.25199275,"remaining_time":19.57299679},
{"learn":[0.1428078631],"iteration":416,"passed_time":44.34442958,"remaining_time":19.46050507},
{"learn":[0.1427811759],"iteration":417,"passed_time":44.45089782,"remaining_time":19.35421867},
{"learn":[0.14276016],"iteration":418,"passed_time":44.54648085,"remaining_time":19.2432292},
{"learn":[0.142732439],"iteration":419,"passed_time":44.65135976,"remaining_time":19.13629704},
{"learn":[0.1427029905],"iteration":420,"passed_time":44.7507321,"remaining_time":19.02703336},
{"learn":[0.1426858212],"iteration":421,"passed_time":44.84319719,"remaining_time":18.91490308},
{"learn":[0.1426608915],"iteration":422,"passed_time":44.9344374,"remaining_time":18.80235324},
{"learn":[0.1426365105],"iteration":423,"passed_time":45.03182376,"remaining_time":18.69245515},
{"learn":[0.1426181156],"iteration":424,"passed_time":45.12881554,"remaining_time":18.58245346},
{"learn":[0.1425878584],"iteration":425,"passed_time":45.22834495,"remaining_time":18.47354935},
{"learn":[0.1425560355],"iteration":426,"passed_time":45.33019716,"remaining_time":18.36563023},
{"learn":[0.1425324775],"iteration":427,"passed_time":45.43214973,"remaining_time":18.2577798},
{"learn":[0.1425072121],"iteration":428,"passed_time":45.53001164,"remaining_time":18.14832632},
{"learn":[0.1424801313],"iteration":429,"passed_time":45.63007075,"remaining_time":18.03979541},
{"learn":[0.1424351231],"iteration":430,"passed_time":45.72550129,"remaining_time":17.92948891},
{"learn":[0.1424075366],"iteration":431,"passed_time":45.81534717,"remaining_time":17.81707945},
{"learn":[0.1423824168],"iteration":432,"passed_time":45.91045891,"remaining_time":17.70680517},
{"learn":[0.1423674413],"iteration":433,"passed_time":45.99616445,"remaining_time":17.59300299},
{"learn":[0.1423387914],"iteration":434,"passed_time":46.08990624,"remaining_time":17.48237823},
{"learn":[0.1423229509],"iteration":435,"passed_time":46.17747486,"remaining_time":17.36950889},
{"learn":[0.142300969],"iteration":436,"passed_time":46.27128146,"remaining_time":17.2590821},
{"learn":[0.1422893014],"iteration":437,"passed_time":46.35944632,"remaining_time":17.14664453},
{"learn":[0.1422579076],"iteration":438,"passed_time":46.44701619,"remaining_time":17.03409933},
{"learn":[0.1422260923],"iteration":439,"passed_time":46.54352798,"remaining_time":16.92491927},
{"learn":[0.1422049373],"iteration":440,"passed_time":46.63815331,"remaining_time":16.8151165},
{"learn":[0.1421722344],"iteration":441,"passed_time":46.73549048,"remaining_time":16.7063518},
{"learn":[0.1421377647],"iteration":442,"passed_time":46.83270567,"remaining_time":16.59759546},
{"learn":[0.1421125202],"iteration":443,"passed_time":46.93306011,"remaining_time":16.48999409},
{"learn":[0.1420917689],"iteration":444,"passed_time":47.02612622,"remaining_time":16.37988666},
{"learn":[0.1420595748],"iteration":445,"passed_time":47.12694508,"remaining_time":16.27253261},
{"learn":[0.1420060104],"iteration":446,"passed_time":47.22138017,"remaining_time":16.16302274},
{"learn":[0.1419760241],"iteration":447,"passed_time":47.31708757,"remaining_time":16.05401185},
{"learn":[0.1419567773],"iteration":448,"passed_time":47.40461253,"remaining_time":15.94230844},
{"learn":[0.141921435],"iteration":449,"passed_time":47.49964576,"remaining_time":15.83321525},
{"learn":[0.141901765],"iteration":450,"passed_time":47.59344167,"remaining_time":15.72377563},
{"learn":[0.1418824652],"iteration":451,"passed_time":47.70112785,"remaining_time":15.61895337},
{"learn":[0.1418491264],"iteration":452,"passed_time":47.88870858,"remaining_time":15.5400445},
{"learn":[0.1418044249],"iteration":453,"passed_time":48.00437047,"remaining_time":15.43752883},
{"learn":[0.141790751],"iteration":454,"passed_time":48.11261828,"remaining_time":15.33259264},
{"learn":[0.1417701123],"iteration":455,"passed_time":48.21737347,"remaining_time":15.22653899},
{"learn":[0.1417537507],"iteration":456,"passed_time":48.32551395,"remaining_time":15.12155032},
{"learn":[0.1417355018],"iteration":457,"passed_time":48.43558536,"remaining_time":15.01714655},
{"learn":[0.1417127058],"iteration":458,"passed_time":48.56173013,"remaining_time":14.91765566},
{"learn":[0.1416885772],"iteration":459,"passed_time":48.65529136,"remaining_time":14.80813215},
{"learn":[0.1416656448],"iteration":460,"passed_time":48.75314127,"remaining_time":14.69997101},
{"learn":[0.1416543964],"iteration":461,"passed_time":48.84274236,"remaining_time":14.58939057},
{"learn":[0.1416289195],"iteration":462,"passed_time":48.93725495,"remaining_time":14.48035406},
{"learn":[0.1416041464],"iteration":463,"passed_time":49.03910387,"remaining_time":14.37353045},
{"learn":[0.1415659053],"iteration":464,"passed_time":49.14611002,"remaining_time":14.26822549},
{"learn":[0.141539752],"iteration":465,"passed_time":49.24881635,"remaining_time":14.16167681},
{"learn":[0.1415120766],"iteration":466,"passed_time":49.3516717,"remaining_time":14.05518701},
{"learn":[0.1414988535],"iteration":467,"passed_time":49.4439646,"remaining_time":13.9457336},
{"learn":[0.1414780689],"iteration":468,"passed_time":49.54653669,"remaining_time":13.83922453},
{"learn":[0.1414500099],"iteration":469,"passed_time":49.64532847,"remaining_time":13.7316866},
{"learn":[0.1414190017],"iteration":470,"passed_time":49.74428184,"remaining_time":13.62423006},
{"learn":[0.1413987843],"iteration":471,"passed_time":49.83828992,"remaining_time":13.51546845},
{"learn":[0.1413739754],"iteration":472,"passed_time":49.93901721,"remaining_time":13.40857333},
{"learn":[0.1413505475],"iteration":473,"passed_time":50.03946921,"remaining_time":13.30163106},
{"learn":[0.1413250729],"iteration":474,"passed_time":50.13928795,"remaining_time":13.19454946},
{"learn":[0.1413021417],"iteration":475,"passed_time":50.23479895,"remaining_time":13.0863762},
{"learn":[0.1412786056],"iteration":476,"passed_time":50.32918273,"remaining_time":12.97796536},
{"learn":[0.1412680219],"iteration":477,"passed_time":50.41726606,"remaining_time":12.86800515},
{"learn":[0.1412486676],"iteration":478,"passed_time":50.50757014,"remaining_time":12.75869726},
{"learn":[0.1412302861],"iteration":479,"passed_time":50.60503145,"remaining_time":12.65125786},
{"learn":[0.1412118839],"iteration":480,"passed_time":50.69862708,"remaining_time":12.54290358},
{"learn":[0.1411907059],"iteration":481,"passed_time":50.79491638,"remaining_time":12.43526998},
{"learn":[0.1411579865],"iteration":482,"passed_time":50.89553898,"remaining_time":12.32873304},
{"learn":[0.1411328359],"iteration":483,"passed_time":50.98994768,"remaining_time":12.22073126},
{"learn":[0.1411094962],"iteration":484,"passed_time":51.08677945,"remaining_time":12.11336008},
{"learn":[0.1410911834],"iteration":485,"passed_time":51.18081907,"remaining_time":12.00537731},
{"learn":[0.141069994],"iteration":486,"passed_time":51.28134531,"remaining_time":11.89895692},
{"learn":[0.141048972],"iteration":487,"passed_time":51.38127396,"remaining_time":11.79242353},
{"learn":[0.1410298129],"iteration":488,"passed_time":51.47319662,"remaining_time":11.68409985},
{"learn":[0.1409993775],"iteration":489,"passed_time":51.57356185,"remaining_time":11.57773838},
{"learn":[0.1409761178],"iteration":490,"passed_time":51.67018333,"remaining_time":11.47057023},
{"learn":[0.1409515268],"iteration":491,"passed_time":51.76384276,"remaining_time":11.36279475},
{"learn":[0.140929903],"iteration":492,"passed_time":51.86063473,"remaining_time":11.25575642},
{"learn":[0.140921326],"iteration":493,"passed_time":51.95370504,"remaining_time":11.147961},
{"learn":[0.1409020516],"iteration":494,"passed_time":52.05626467,"remaining_time":11.04223796},
{"learn":[0.1408785104],"iteration":495,"passed_time":52.15799789,"remaining_time":10.9363544},
{"learn":[0.140844219],"iteration":496,"passed_time":52.26592428,"remaining_time":10.83177103},
{"learn":[0.1408267929],"iteration":497,"passed_time":52.36578801,"remaining_time":10.72552285},
{"learn":[0.1407966658],"iteration":498,"passed_time":52.47410157,"remaining_time":10.62101054},
{"learn":[0.1407736088],"iteration":499,"passed_time":52.59183759,"remaining_time":10.51836752},
{"learn":[0.1407534693],"iteration":500,"passed_time":52.73339943,"remaining_time":10.42037234},
{"learn":[0.1407320655],"iteration":501,"passed_time":52.86729647,"remaining_time":10.32070728},
{"learn":[0.1407050863],"iteration":502,"passed_time":52.99028438,"remaining_time":10.21880235},
{"learn":[0.1406940415],"iteration":503,"passed_time":53.09997347,"remaining_time":10.11428066},
{"learn":[0.140679246],"iteration":504,"passed_time":53.22014023,"remaining_time":10.01170955},
{"learn":[0.1406581459],"iteration":505,"passed_time":53.33581371,"remaining_time":9.908234168},
{"learn":[0.1406327782],"iteration":506,"passed_time":53.45837566,"remaining_time":9.805974234},
{"learn":[0.140600572],"iteration":507,"passed_time":53.5760198,"remaining_time":9.702743743},
{"learn":[0.1405775847],"iteration":508,"passed_time":53.69453106,"remaining_time":9.599611643},
{"learn":[0.1405541028],"iteration":509,"passed_time":53.78796655,"remaining_time":9.491994097},
{"learn":[0.1405353087],"iteration":510,"passed_time":53.89701792,"remaining_time":9.387151849},
{"learn":[0.1405177024],"iteration":511,"passed_time":54.00922846,"remaining_time":9.282836141},
{"learn":[0.1404854915],"iteration":512,"passed_time":54.11185177,"remaining_time":9.17686375},
{"learn":[0.1404683725],"iteration":513,"passed_time":54.206584,"remaining_time":9.069584094},
{"learn":[0.1404462246],"iteration":514,"passed_time":54.29641633,"remaining_time":8.961544442},
{"learn":[0.1404268723],"iteration":515,"passed_time":54.38603985,"remaining_time":8.853541371},
{"learn":[0.1403983251],"iteration":516,"passed_time":54.4855358,"remaining_time":8.747194335},
{"learn":[0.1403722929],"iteration":517,"passed_time":54.59387987,"remaining_time":8.642274419},
{"learn":[0.1403508534],"iteration":518,"passed_time":54.69084087,"remaining_time":8.53556476},
{"learn":[0.1403198179],"iteration":519,"passed_time":54.79189378,"remaining_time":8.429522121},
{"learn":[0.1402988072],"iteration":520,"passed_time":54.88668862,"remaining_time":8.322549714},
{"learn":[0.140276607],"iteration":521,"passed_time":54.9844122,"remaining_time":8.216061593},
{"learn":[0.1402370996],"iteration":522,"passed_time":55.08130782,"remaining_time":8.10948509},
{"learn":[0.1402090668],"iteration":523,"passed_time":55.17814308,"remaining_time":8.002936783},
{"learn":[0.1401852885],"iteration":524,"passed_time":55.27654557,"remaining_time":7.896649367},
{"learn":[0.1401630275],"iteration":525,"passed_time":55.37324046,"remaining_time":7.7901517},
{"learn":[0.1401404379],"iteration":526,"passed_time":55.47214233,"remaining_time":7.683996945},
{"learn":[0.1401185376],"iteration":527,"passed_time":55.57051882,"remaining_time":7.577798021},
{"learn":[0.140101757],"iteration":528,"passed_time":55.66713185,"remaining_time":7.471391988},
{"learn":[0.1400843418],"iteration":529,"passed_time":55.76001802,"remaining_time":7.364530682},
{"learn":[0.1400636183],"iteration":530,"passed_time":55.84938322,"remaining_time":7.257264486},
{"learn":[0.14003945],"iteration":531,"passed_time":55.93955026,"remaining_time":7.150168078},
{"learn":[0.1400291436],"iteration":532,"passed_time":56.02540819,"remaining_time":7.042593525},
{"learn":[0.1400054483],"iteration":533,"passed_time":56.12023424,"remaining_time":6.936208727},
{"learn":[0.1399801217],"iteration":534,"passed_time":56.21510794,"remaining_time":6.829872927},
{"learn":[0.1399549526],"iteration":535,"passed_time":56.31093813,"remaining_time":6.723694105},
{"learn":[0.139929248],"iteration":536,"passed_time":56.40362281,"remaining_time":6.617184799},
{"learn":[0.1399077404],"iteration":537,"passed_time":56.50560845,"remaining_time":6.511798743},
{"learn":[0.1398887738],"iteration":538,"passed_time":56.60570466,"remaining_time":6.406211473},
{"learn":[0.1398632168],"iteration":539,"passed_time":56.70869614,"remaining_time":6.300966238},
{"learn":[0.1398485656],"iteration":540,"passed_time":56.79836763,"remaining_time":6.194276692},
{"learn":[0.1398235583],"iteration":541,"passed_time":56.89645922,"remaining_time":6.088550987},
{"learn":[0.1398011475],"iteration":542,"passed_time":56.99517069,"remaining_time":5.98291847},
{"learn":[0.13977824],"iteration":543,"passed_time":57.09766518,"remaining_time":5.877700827},
{"learn":[0.1397528358],"iteration":544,"passed_time":57.19725621,"remaining_time":5.772200168},
{"learn":[0.1397325768],"iteration":545,"passed_time":57.29914703,"remaining_time":5.666948607},
{"learn":[0.1397134941],"iteration":546,"passed_time":57.39511042,"remaining_time":5.561135013},
{"learn":[0.139692705],"iteration":547,"passed_time":57.49258765,"remaining_time":5.455501018},
{"learn":[0.1396793263],"iteration":548,"passed_time":57.58642193,"remaining_time":5.349558321},
{"learn":[0.1396602335],"iteration":549,"passed_time":57.68701867,"remaining_time":5.244274424},
{"learn":[0.1396489074],"iteration":550,"passed_time":57.78372927,"remaining_time":5.138661949},
{"learn":[0.1396264291],"iteration":551,"passed_time":57.8936154,"remaining_time":5.034227426},
{"learn":[0.1396117166],"iteration":552,"passed_time":57.99228278,"remaining_time":4.928819693},
{"learn":[0.1395958855],"iteration":553,"passed_time":58.10298643,"remaining_time":4.824435696},
{"learn":[0.139577181],"iteration":554,"passed_time":58.21480252,"remaining_time":4.720119123},
{"learn":[0.1395506051],"iteration":555,"passed_time":58.32590496,"remaining_time":4.615719098},
{"learn":[0.1395279157],"iteration":556,"passed_time":58.44813874,"remaining_time":4.512154337},
{"learn":[0.1395198017],"iteration":557,"passed_time":58.56678121,"remaining_time":4.408252349},
{"learn":[0.1395018376],"iteration":558,"passed_time":58.69316586,"remaining_time":4.304865474},
{"learn":[0.1394889962],"iteration":559,"passed_time":58.78455204,"remaining_time":4.198896574},
{"learn":[0.1394566419],"iteration":560,"passed_time":58.88648744,"remaining_time":4.093713031},
{"learn":[0.1394374308],"iteration":561,"passed_time":58.99212025,"remaining_time":3.988791049},
{"learn":[0.139413321],"iteration":562,"passed_time":59.09232062,"remaining_time":3.883509526},
{"learn":[0.1393933297],"iteration":563,"passed_time":59.19788297,"remaining_time":3.778588275},
{"learn":[0.1393702266],"iteration":564,"passed_time":59.29572796,"remaining_time":3.673186688},
{"learn":[0.1393532005],"iteration":565,"passed_time":59.39154765,"remaining_time":3.567690141},
{"learn":[0.1393283831],"iteration":566,"passed_time":59.50052278,"remaining_time":3.462993389},
{"learn":[0.1393059556],"iteration":567,"passed_time":59.59204064,"remaining_time":3.357298064},
{"learn":[0.1392854952],"iteration":568,"passed_time":59.68997559,"remaining_time":3.252002185},
{"learn":[0.1392521908],"iteration":569,"passed_time":59.79042197,"remaining_time":3.146864314},
{"learn":[0.1392337143],"iteration":570,"passed_time":59.88632782,"remaining_time":3.041512271},
{"learn":[0.1392193741],"iteration":571,"passed_time":59.97611986,"remaining_time":2.935893979},
{"learn":[0.1392025855],"iteration":572,"passed_time":60.07449112,"remaining_time":2.830735184},
{"learn":[0.1391832566],"iteration":573,"passed_time":60.17575971,"remaining_time":2.725731276},
{"learn":[0.1391576173],"iteration":574,"passed_time":60.27240798,"remaining_time":2.620539477},
{"learn":[0.1391325434],"iteration":575,"passed_time":60.37497102,"remaining_time":2.515623793},
{"learn":[0.1391068503],"iteration":576,"passed_time":60.47498802,"remaining_time":2.410614774},
{"learn":[0.1390928659],"iteration":577,"passed_time":60.56278409,"remaining_time":2.305157872},
{"learn":[0.1390791923],"iteration":578,"passed_time":60.65778491,"remaining_time":2.200023287},
{"learn":[0.1390542725],"iteration":579,"passed_time":60.74842838,"remaining_time":2.094773392},
{"learn":[0.1390364648],"iteration":580,"passed_time":60.83428888,"remaining_time":1.989417365},
{"learn":[0.139022306],"iteration":581,"passed_time":60.92352803,"remaining_time":1.884232826},
{"learn":[0.1389991282],"iteration":582,"passed_time":61.0243422,"remaining_time":1.77944051},
{"learn":[0.1389681479],"iteration":583,"passed_time":61.12110091,"remaining_time":1.67455071},
{"learn":[0.1389469266],"iteration":584,"passed_time":61.21597582,"remaining_time":1.569640406},
{"learn":[0.1389300458],"iteration":585,"passed_time":61.30779939,"remaining_time":1.464691453},
{"learn":[0.1389227318],"iteration":586,"passed_time":61.39679008,"remaining_time":1.359724482},
{"learn":[0.1389037499],"iteration":587,"passed_time":61.48870472,"remaining_time":1.254871525},
{"learn":[0.1388915432],"iteration":588,"passed_time":61.58563814,"remaining_time":1.15015623},
{"learn":[0.1388691086],"iteration":589,"passed_time":61.68821914,"remaining_time":1.045563036},
{"learn":[0.1388463929],"iteration":590,"passed_time":61.78530332,"remaining_time":0.940892944},
{"learn":[0.1388229455],"iteration":591,"passed_time":61.88553175,"remaining_time":0.8362909696},
{"learn":[0.1388018104],"iteration":592,"passed_time":61.98544141,"remaining_time":0.7316999829},
{"learn":[0.1387836905],"iteration":593,"passed_time":62.0744362,"remaining_time":0.6270145071},
{"learn":[0.1387617476],"iteration":594,"passed_time":62.17217953,"remaining_time":0.5224552901},
{"learn":[0.138728028],"iteration":595,"passed_time":62.27755514,"remaining_time":0.4179701687},
{"learn":[0.138707772],"iteration":596,"passed_time":62.37025701,"remaining_time":0.3134183769},
{"learn":[0.138693226],"iteration":597,"passed_time":62.47543951,"remaining_time":0.2089479582},
{"learn":[0.1386678174],"iteration":598,"passed_time":62.58791158,"remaining_time":0.1044873315},
{"learn":[0.1386382718],"iteration":599,"passed_time":62.71541963,"remaining_time":0}
]}